jitsu/__init__.py
jitsu/__main__.py
jitsu/__version__.py
jitsu-0.0.1.dist-info/METADATA
jitsu-0.0.1.dist-info/RECORD
jitsu-0.0.1.dist-info/WHEEL
jitsu-0.0.1.dist-info/entry_points.txt
jitsu-0.0.1.dist-info/top_level.txt
