Metadata-Version: 2.1
Name: jitsu
Version: 0.0.1
Summary: Jinja2 templates rendering from yaml data.
Home-page: https://github.com/meetmangukiya/jitsu
Author: Meet Mangukiya
Author-email: meetmangukiya98@gmail.com
License: MIT
Platform: UNKNOWN
Classifier: License :: OSI Approved :: MIT License
Classifier: Programming Language :: Python
Classifier: Programming Language :: Python :: 3
Classifier: Programming Language :: Python :: 3.6
Classifier: Programming Language :: Python :: Implementation :: CPython
Classifier: Programming Language :: Python :: Implementation :: PyPy
Requires-Python: >=3.6.0
Requires-Dist: jinja2
Requires-Dist: pyyaml
